dumptls/__init__.py
dumptls/cli.py
dumptls-0.5.4.dist-info/LICENSE
dumptls-0.5.4.dist-info/METADATA
dumptls-0.5.4.dist-info/WHEEL
dumptls-0.5.4.dist-info/entry_points.txt
dumptls-0.5.4.dist-info/top_level.txt
dumptls-0.5.4.dist-info/RECORD
