Metadata-Version: 2.1
Name: dumptls
Version: 0.5.4
Summary: A tool to download TLS certificates including intermediate and root CA certs
Home-page: https://github.com/SCGIS-Wales/dumptls
Author: Dejan Gregor
Author-email: developer@cloudfever.uk
Project-URL: Documentation, https://github.com/SCGIS-Wales/dumptls#readme
Project-URL: Source, https://github.com/SCGIS-Wales/dumptls
Project-URL: Tracker, https://github.com/SCGIS-Wales/dumptls/issues
Classifier: Programming Language :: Python :: 3
Classifier: License :: OSI Approved :: MIT License
Classifier: Operating System :: OS Independent
Classifier: Development Status :: 4 - Beta
Classifier: Intended Audience :: Developers
Classifier: Topic :: Software Development :: Libraries :: Python Modules
Requires-Python: >=3.6
License-File: LICENSE
Requires-Dist: click
Requires-Dist: pyopenssl
